sklearnreg/__init__.py
sklearnreg-0.0.2.dist-info/LICENSE.txt
sklearnreg-0.0.2.dist-info/METADATA
sklearnreg-0.0.2.dist-info/WHEEL
sklearnreg-0.0.2.dist-info/top_level.txt
sklearnreg-0.0.2.dist-info/RECORD
