Metadata-Version: 2.1
Name: sklearnreg
Version: 0.0.2
Summary: a library importing all the classes of regression
Home-page: https://github.com/Sagu12
Author: ['Sagnik Banerjee', 'Ankit Raj']
Author-email: sagu7065@gmail.com
License: UNKNOWN
Platform: UNKNOWN
Classifier: Programming Language :: Python :: 3
Classifier: License :: OSI Approved :: MIT License
Classifier: Operating System :: OS Independent
